hazm/__init__.py
hazm/api.py
hazm/chunker.py
hazm/constants.py
hazm/corpus_readers/__init__.py
hazm/corpus_readers/arman_reader.py
hazm/corpus_readers/bijankhan_reader.py
hazm/corpus_readers/dadegan_reader.py
hazm/corpus_readers/degarbayan_reader.py
hazm/corpus_readers/faspell_reader.py
hazm/corpus_readers/hamshahri_reader.py
hazm/corpus_readers/mirastext_reader.py
hazm/corpus_readers/mizan_reader.py
hazm/corpus_readers/naab_reader.py
hazm/corpus_readers/ner_reader.py
hazm/corpus_readers/persian_plain_text_reader.py
hazm/corpus_readers/persica_reader.py
hazm/corpus_readers/peykare_reader.py
hazm/corpus_readers/pn_summary_reader.py
hazm/corpus_readers/quran_reader.py
hazm/corpus_readers/sentipers_reader.py
hazm/corpus_readers/tnews_reader.py
hazm/corpus_readers/treebank_reader.py
hazm/corpus_readers/universal_dadegan_reader.py
hazm/corpus_readers/verbvalency_reader.py
hazm/corpus_readers/wiki_extractor.py
hazm/corpus_readers/wikipedia_reader.py
hazm/data/abbreviations.dat
hazm/data/iverbs.dat
hazm/data/iwords.dat
hazm/data/stopwords.dat
hazm/data/verbs.dat
hazm/data/words.dat
hazm/dependency_parser.py
hazm/embedding.py
hazm/informal_normalizer.py
hazm/lemmatizer.py
hazm/ner.py
hazm/normalizer.py
hazm/pos_tagger.py
hazm/sentence_tokenizer.py
hazm/sequence_tagger.py
hazm/stemmer.py
hazm/token_splitter.py
hazm/types.py
hazm/utils.py
hazm/word_tokenizer.py
hazm-0.11.0.dist-info/METADATA
hazm-0.11.0.dist-info/WHEEL
hazm-0.11.0.dist-info/licenses/LICENSE
hazm-0.11.0.dist-info/RECORD
