Metadata-Version: 2.4
Name: hazm
Version: 0.11.0
Summary: Persian NLP Toolkit
License: MIT
License-File: LICENSE
Keywords: nlp,persian nlp,persian
Author: Roshan
Author-email: salam@roshan-ai.com
Maintainer: Roshan
Maintainer-email: salam@roshan-ai.com
Requires-Python: >=3.12,<3.14
Classifier: Intended Audience :: Developers
Classifier: License :: OSI Approved :: MIT License
Classifier: Natural Language :: Persian
Classifier: Programming Language :: Python :: 3
Classifier: Programming Language :: Python :: 3.12
Classifier: Programming Language :: Python :: 3.13
Classifier: Topic :: Text Processing
Requires-Dist: flashtext (>=2.7,<3.0)
Requires-Dist: gensim (>=4.4.0,<5.0.0)
Requires-Dist: huggingface-hub (>=0.34.0,<0.35.0)
Requires-Dist: nltk (>=3.9.2,<4.0.0)
Requires-Dist: numpy (>=2.0.0,<3.0.0)
Requires-Dist: python-crfsuite (>=0.9.11,<0.10.0)
Requires-Dist: scikit-learn (>=1.7.2,<2.0.0)
Requires-Dist: smart-open (>=7.5.0,<8.0.0)
Requires-Dist: spacy (>=3.8.11,<4.0.0)
Requires-Dist: spacy-transformers (>=1.3.4,<2.0.0)
Requires-Dist: tqdm (>=4.67.1,<5.0.0)
Project-URL: Changelog, https://github.com/roshan-research/hazm/releases/latest
Project-URL: Contribution, https://github.com/roshan-research/hazm/blob/master/CONTRIBUTION.md
Project-URL: Documentation, https://roshan-ai.ir/hazm/docs/
Project-URL: Demo, https://www.roshan-ai.ir/hazm/demo/
Project-URL: Issues, https://github.com/roshan-research/hazm/issues
Project-URL: Join-us, https://www.roshan-ai.ir/join-us/
Project-URL: Repository, https://github.com/roshan-research/hazm/
